skblocks/__init__.py
skblocks/common.py
skblocks/transformers.py
tests/__init__.py
tests/test_basic.py
scikit_blocks-0.0.1.dist-info/METADATA
scikit_blocks-0.0.1.dist-info/WHEEL
scikit_blocks-0.0.1.dist-info/top_level.txt
scikit_blocks-0.0.1.dist-info/RECORD
